aliasify/about_author.py
aliasify/aliasify.py
aliasify/configs.py
aliasify/crud.py
aliasify/sync.py
aliasify/assets/alerts.py
aliasify/assets/assets.py
aliasify_cli-1.0.3.dist-info/METADATA
aliasify_cli-1.0.3.dist-info/WHEEL
aliasify_cli-1.0.3.dist-info/entry_points.txt
aliasify_cli-1.0.3.dist-info/top_level.txt
aliasify_cli-1.0.3.dist-info/RECORD
