Metadata-Version: 2.4
Name: aliasify-cli
Version: 1.0.3
Summary: Aliases Keeper - Manage and synchronize your aliases
Author-email: Your Name <your.email@example.com>
Requires-Python: >=3.7
Requires-Dist: typer[all]>=0.9.0
Requires-Dist: python-dotenv>=0.19.0
Requires-Dist: gitpython>=3.1.0
Requires-Dist: pyyaml>=6.0.1
